setup.py
django_intruder.egg-info/PKG-INFO
django_intruder.egg-info/SOURCES.txt
django_intruder.egg-info/dependency_links.txt
django_intruder.egg-info/top_level.txt
example/__init__.py
example/urls.py
example/views.py
intruder/__init__.py
intruder/admin.py
intruder/middleware.py
intruder/models.py
intruder/urls.py
intruder/views.py
intruder/tests/__init__.py
intruder/tests/test_admin.py
intruder/tests/test_middleware.py
intruder/tests/test_models.py
intruder/tests/__init__.py
intruder/tests/test_admin.py
intruder/tests/test_middleware.py
intruder/tests/test_models.py