Metadata-Version: 1.0
Name: django-intruder
Version: 0.1.3
Summary: Django Intruder is a simple and unobtrusive application to intercept requests. It is useful to enable and disable features, for continuous deployment purpouses.
Home-page: https://bitbucket.org/paulocheque/django-intruder
Author: paulocheque
Author-email: paulocheque@gmail.com
License: MIT
Keywords: python django intruder feature flip feature switch
Platform: UNKNOWN
